<?xml version="1.0" encoding="UTF-8"?>
<export version="E">
  <design>
    <source>/home/johannes/Documents/Electronics/Framework/Expansioncards/CAN/Electrical/CAN.kicad_sch</source>
    <date>Tue 15 Aug 2023 10:41:07 PM JST</date>
    <tool>Eeschema 7.0.6</tool>
    <sheet number="1" name="/" tstamps="/">
      <title_block>
        <title>Expansion Card Template</title>
        <company>Framework</company>
        <rev>X1</rev>
        <date>2020-12-12</date>
        <source>CAN.kicad_sch</source>
        <comment number="1" value="This work is licensed under a Creative Commons Attribution 4.0 International License"/>
        <comment number="2" value=""/>
        <comment number="3" value=""/>
        <comment number="4" value="https://frame.work"/>
        <comment number="5" value=""/>
        <comment number="6" value=""/>
        <comment number="7" value=""/>
        <comment number="8" value=""/>
        <comment number="9" value=""/>
      </title_block>
    </sheet>
  </design>
  <components>
    <comp ref="C1">
      <value>10uF</value>
      <footprint>Capacitor_SMD:C_0603_1608Metric_Pad1.08x0.95mm_HandSolder</footprint>
      <libsource lib="Device" part="C_Small" description="Unpolarized capacitor, small symbol"/>
      <property name="Sheetname" value=""/>
      <property name="Sheetfile" value="CAN.kicad_sch"/>
      <property name="ki_description" value="Unpolarized capacitor, small symbol"/>
      <property name="ki_keywords" value="capacitor cap"/>
      <sheetpath names="/" tstamps="/"/>
      <tstamps>00000000-0000-0000-0000-00005fd33d8e</tstamps>
    </comp>
    <comp ref="C2">
      <value>10uF</value>
      <footprint>Capacitor_SMD:C_0603_1608Metric_Pad1.08x0.95mm_HandSolder</footprint>
      <libsource lib="Device" part="C_Small" description="Unpolarized capacitor, small symbol"/>
      <property name="Sheetname" value=""/>
      <property name="Sheetfile" value="CAN.kicad_sch"/>
      <property name="ki_description" value="Unpolarized capacitor, small symbol"/>
      <property name="ki_keywords" value="capacitor cap"/>
      <sheetpath names="/" tstamps="/"/>
      <tstamps>00000000-0000-0000-0000-00005fd346b0</tstamps>
    </comp>
    <comp ref="C3">
      <value>22uF</value>
      <footprint>Capacitor_SMD:C_0603_1608Metric_Pad1.08x0.95mm_HandSolder</footprint>
      <libsource lib="Device" part="C" description="Unpolarized capacitor"/>
      <property name="Sheetname" value=""/>
      <property name="Sheetfile" value="CAN.kicad_sch"/>
      <property name="ki_description" value="Unpolarized capacitor"/>
      <property name="ki_keywords" value="cap capacitor"/>
      <sheetpath names="/" tstamps="/"/>
      <tstamps>0845d5d0-fd15-4353-a476-63d5adc4cc28</tstamps>
    </comp>
    <comp ref="C4">
      <value>100nF</value>
      <footprint>Capacitor_SMD:C_0603_1608Metric_Pad1.08x0.95mm_HandSolder</footprint>
      <libsource lib="Device" part="C" description="Unpolarized capacitor"/>
      <property name="Sheetname" value=""/>
      <property name="Sheetfile" value="CAN.kicad_sch"/>
      <property name="ki_description" value="Unpolarized capacitor"/>
      <property name="ki_keywords" value="cap capacitor"/>
      <sheetpath names="/" tstamps="/"/>
      <tstamps>e3f238e0-9346-499a-b2d5-a31b593f9225</tstamps>
    </comp>
    <comp ref="H1">
      <value>MountingHole</value>
      <footprint>MountingHole:MountingHole_2.2mm_M2</footprint>
      <libsource lib="Mechanical" part="MountingHole" description="Mounting Hole without connection"/>
      <property name="Sheetname" value=""/>
      <property name="Sheetfile" value="CAN.kicad_sch"/>
      <property name="ki_description" value="Mounting Hole without connection"/>
      <property name="ki_keywords" value="mounting hole"/>
      <sheetpath names="/" tstamps="/"/>
      <tstamps>00000000-0000-0000-0000-00005fdb1a76</tstamps>
    </comp>
    <comp ref="H2">
      <value>MountingHole</value>
      <footprint>MountingHole:MountingHole_2.2mm_M2</footprint>
      <libsource lib="Mechanical" part="MountingHole" description="Mounting Hole without connection"/>
      <property name="Sheetname" value=""/>
      <property name="Sheetfile" value="CAN.kicad_sch"/>
      <property name="ki_description" value="Mounting Hole without connection"/>
      <property name="ki_keywords" value="mounting hole"/>
      <sheetpath names="/" tstamps="/"/>
      <tstamps>00000000-0000-0000-0000-00005fdb2fce</tstamps>
    </comp>
    <comp ref="J1">
      <value>Conn_01x04</value>
      <footprint>Connector_PinSocket_2.54mm:PinSocket_1x04_P2.54mm_Horizontal</footprint>
      <libsource lib="Connector_Generic" part="Conn_01x04" description="Generic connector, single row, 01x04, script generated (kicad-library-utils/schlib/autogen/connector/)"/>
      <property name="Sheetname" value=""/>
      <property name="Sheetfile" value="CAN.kicad_sch"/>
      <property name="ki_description" value="Generic connector, single row, 01x04, script generated (kicad-library-utils/schlib/autogen/connector/)"/>
      <property name="ki_keywords" value="connector"/>
      <sheetpath names="/" tstamps="/"/>
      <tstamps>89bf799d-9927-4bcd-b57b-eceaa1461421</tstamps>
    </comp>
    <comp ref="P1">
      <value>USB_C_Plug_USB2.0</value>
      <datasheet>https://www.usb.org/sites/default/files/documents/usb_type-c.zip</datasheet>
      <libsource lib="Connector" part="USB_C_Plug_USB2.0" description="USB 2.0-only Type-C Plug connector"/>
      <property name="Sheetname" value=""/>
      <property name="Sheetfile" value="CAN.kicad_sch"/>
      <property name="ki_description" value="USB 2.0-only Type-C Plug connector"/>
      <property name="ki_keywords" value="usb universal serial bus type-C USB2.0"/>
      <sheetpath names="/" tstamps="/"/>
      <tstamps>00000000-0000-0000-0000-00005fd76bc6</tstamps>
    </comp>
    <comp ref="Q1">
      <value>BSS214NW</value>
      <footprint>Package_TO_SOT_SMD:SOT-323_SC-70</footprint>
      <datasheet>https://www.infineon.com/dgdl/Infineon-BSS214NW-DS-v02_02-en.pdf?fileId=db3a30431b3e89eb011b695aebc01bde</datasheet>
      <libsource lib="Transistor_FET" part="BSS214NW" description="20V Vds, 1.5A Id, N-Channel MOSFET, SOT-323"/>
      <property name="Sheetname" value=""/>
      <property name="Sheetfile" value="CAN.kicad_sch"/>
      <property name="ki_description" value="20V Vds, 1.5A Id, N-Channel MOSFET, SOT-323"/>
      <property name="ki_keywords" value="N-Channel MOSFET"/>
      <sheetpath names="/" tstamps="/"/>
      <tstamps>e6f1b047-affa-4830-898f-52ad7224b4a9</tstamps>
    </comp>
    <comp ref="Q2">
      <value>BSS214NW</value>
      <footprint>Package_TO_SOT_SMD:SOT-323_SC-70</footprint>
      <datasheet>https://www.infineon.com/dgdl/Infineon-BSS214NW-DS-v02_02-en.pdf?fileId=db3a30431b3e89eb011b695aebc01bde</datasheet>
      <libsource lib="Transistor_FET" part="BSS214NW" description="20V Vds, 1.5A Id, N-Channel MOSFET, SOT-323"/>
      <property name="Sheetname" value=""/>
      <property name="Sheetfile" value="CAN.kicad_sch"/>
      <property name="ki_description" value="20V Vds, 1.5A Id, N-Channel MOSFET, SOT-323"/>
      <property name="ki_keywords" value="N-Channel MOSFET"/>
      <sheetpath names="/" tstamps="/"/>
      <tstamps>2d4ff649-f273-4c02-8128-40f18c1a9671</tstamps>
    </comp>
    <comp ref="R1">
      <value>5.1k</value>
      <footprint>Resistor_SMD:R_0603_1608Metric_Pad0.98x0.95mm_HandSolder</footprint>
      <libsource lib="Device" part="R" description="Resistor"/>
      <property name="Sheetname" value=""/>
      <property name="Sheetfile" value="CAN.kicad_sch"/>
      <property name="ki_description" value="Resistor"/>
      <property name="ki_keywords" value="R res resistor"/>
      <sheetpath names="/" tstamps="/"/>
      <tstamps>de3b1539-d8a4-4fce-a5c4-9e7dea09456e</tstamps>
    </comp>
    <comp ref="R2">
      <value>60R</value>
      <footprint>Resistor_SMD:R_0603_1608Metric_Pad0.98x0.95mm_HandSolder</footprint>
      <libsource lib="Device" part="R" description="Resistor"/>
      <property name="Sheetname" value=""/>
      <property name="Sheetfile" value="CAN.kicad_sch"/>
      <property name="ki_description" value="Resistor"/>
      <property name="ki_keywords" value="R res resistor"/>
      <sheetpath names="/" tstamps="/"/>
      <tstamps>d169e918-1ff5-4633-a750-0e5e454184ed</tstamps>
    </comp>
    <comp ref="R3">
      <value>60R</value>
      <footprint>Resistor_SMD:R_0603_1608Metric_Pad0.98x0.95mm_HandSolder</footprint>
      <libsource lib="Device" part="R" description="Resistor"/>
      <property name="Sheetname" value=""/>
      <property name="Sheetfile" value="CAN.kicad_sch"/>
      <property name="ki_description" value="Resistor"/>
      <property name="ki_keywords" value="R res resistor"/>
      <sheetpath names="/" tstamps="/"/>
      <tstamps>e3364b3f-e7a5-48a4-b0bb-9b0803aefba3</tstamps>
    </comp>
    <comp ref="TP1">
      <value>TestPoint</value>
      <footprint>TestPoint:TestPoint_Pad_1.5x1.5mm</footprint>
      <libsource lib="Connector" part="TestPoint" description="test point"/>
      <property name="Sheetname" value=""/>
      <property name="Sheetfile" value="CAN.kicad_sch"/>
      <property name="ki_description" value="test point"/>
      <property name="ki_keywords" value="test point tp"/>
      <sheetpath names="/" tstamps="/"/>
      <tstamps>00000000-0000-0000-0000-0000606a89a3</tstamps>
    </comp>
    <comp ref="TP2">
      <value>TestPoint</value>
      <footprint>TestPoint:TestPoint_Pad_1.5x1.5mm</footprint>
      <libsource lib="Connector" part="TestPoint" description="test point"/>
      <property name="Sheetname" value=""/>
      <property name="Sheetfile" value="CAN.kicad_sch"/>
      <property name="ki_description" value="test point"/>
      <property name="ki_keywords" value="test point tp"/>
      <sheetpath names="/" tstamps="/"/>
      <tstamps>00000000-0000-0000-0000-0000606a78c1</tstamps>
    </comp>
    <comp ref="TP3">
      <value>TestPoint</value>
      <footprint>TestPoint:TestPoint_Pad_1.5x1.5mm</footprint>
      <libsource lib="Connector" part="TestPoint" description="test point"/>
      <property name="Sheetname" value=""/>
      <property name="Sheetfile" value="CAN.kicad_sch"/>
      <property name="ki_description" value="test point"/>
      <property name="ki_keywords" value="test point tp"/>
      <sheetpath names="/" tstamps="/"/>
      <tstamps>00000000-0000-0000-0000-0000606a8c9b</tstamps>
    </comp>
    <comp ref="TP4">
      <value>TestPoint</value>
      <footprint>TestPoint:TestPoint_Pad_1.5x1.5mm</footprint>
      <libsource lib="Connector" part="TestPoint" description="test point"/>
      <property name="Sheetname" value=""/>
      <property name="Sheetfile" value="CAN.kicad_sch"/>
      <property name="ki_description" value="test point"/>
      <property name="ki_keywords" value="test point tp"/>
      <sheetpath names="/" tstamps="/"/>
      <tstamps>00000000-0000-0000-0000-0000606a8e98</tstamps>
    </comp>
    <comp ref="U1">
      <value>AP2112K-3.3</value>
      <footprint>Package_TO_SOT_SMD:SOT-23-5</footprint>
      <datasheet>https://www.diodes.com/assets/Datasheets/AP2112.pdf</datasheet>
      <libsource lib="Regulator_Linear" part="AP2112K-3.3" description="600mA low dropout linear regulator, with enable pin, 3.8V-6V input voltage range, 3.3V fixed positive output, SOT-23-5"/>
      <property name="Sheetname" value=""/>
      <property name="Sheetfile" value="CAN.kicad_sch"/>
      <property name="ki_description" value="600mA low dropout linear regulator, with enable pin, 3.8V-6V input voltage range, 3.3V fixed positive output, SOT-23-5"/>
      <property name="ki_keywords" value="linear regulator ldo fixed positive"/>
      <sheetpath names="/" tstamps="/"/>
      <tstamps>00000000-0000-0000-0000-00005fd33096</tstamps>
    </comp>
    <comp ref="U2">
      <value>SN65HVD230</value>
      <footprint>Package_SO:SOIC-8_3.9x4.9mm_P1.27mm</footprint>
      <datasheet>http://www.ti.com/lit/ds/symlink/sn65hvd230.pdf</datasheet>
      <libsource lib="Interface_CAN_LIN" part="SN65HVD230" description="CAN Bus Transceivers, 3.3V, 1Mbps, Low-Power capabilities, SOIC-8"/>
      <property name="Sheetname" value=""/>
      <property name="Sheetfile" value="CAN.kicad_sch"/>
      <property name="ki_description" value="CAN Bus Transceivers, 3.3V, 1Mbps, Low-Power capabilities, SOIC-8"/>
      <property name="ki_keywords" value="can transeiver ti low-power"/>
      <sheetpath names="/" tstamps="/"/>
      <tstamps>93f21074-b9f1-45c6-98fc-141d64855a9d</tstamps>
    </comp>
    <comp ref="U5">
      <value>ESP32-C3-MINI-1</value>
      <footprint>Espressif:ESP32-C3-MINI-1U</footprint>
      <datasheet>https://www.espressif.com/sites/default/files/documentation/esp32-c3-mini-1_datasheet_en.pdf</datasheet>
      <libsource lib="Espressif" part="ESP32-C3-MINI-1" description="ESP32-C3-MINI-1 family is an ultra-low-power MCU-based SoC solution that supports 2.4 GHz Wi-Fi and Bluetooth®Low Energy (Bluetooth LE)."/>
      <property name="Sheetname" value=""/>
      <property name="Sheetfile" value="CAN.kicad_sch"/>
      <property name="ki_description" value="ESP32-C3-MINI-1 family is an ultra-low-power MCU-based SoC solution that supports 2.4 GHz Wi-Fi and Bluetooth®Low Energy (Bluetooth LE)."/>
      <property name="ki_keywords" value="esp32-c3"/>
      <sheetpath names="/" tstamps="/"/>
      <tstamps>fedd55f9-42ca-4799-bcf1-7b7a4d004273</tstamps>
    </comp>
  </components>
  <libparts>
    <libpart lib="Connector" part="TestPoint">
      <description>test point</description>
      <docs>~</docs>
      <footprints>
        <fp>Pin*</fp>
        <fp>Test*</fp>
      </footprints>
      <fields>
        <field name="Reference">TP</field>
        <field name="Value">TestPoint</field>
        <field name="Datasheet">~</field>
      </fields>
      <pins>
        <pin num="1" name="1" type="passive"/>
      </pins>
    </libpart>
    <libpart lib="Connector" part="USB_C_Plug_USB2.0">
      <description>USB 2.0-only Type-C Plug connector</description>
      <docs>https://www.usb.org/sites/default/files/documents/usb_type-c.zip</docs>
      <footprints>
        <fp>USB*C*Plug*</fp>
      </footprints>
      <fields>
        <field name="Reference">P</field>
        <field name="Value">USB_C_Plug_USB2.0</field>
        <field name="Datasheet">https://www.usb.org/sites/default/files/documents/usb_type-c.zip</field>
      </fields>
      <pins>
        <pin num="A1" name="GND" type="passive"/>
        <pin num="A4" name="VBUS" type="passive"/>
        <pin num="A5" name="CC" type="bidirectional"/>
        <pin num="A6" name="D+" type="bidirectional"/>
        <pin num="A7" name="D-" type="bidirectional"/>
        <pin num="A9" name="VBUS" type="passive"/>
        <pin num="A12" name="GND" type="passive"/>
        <pin num="B1" name="GND" type="passive"/>
        <pin num="B4" name="VBUS" type="passive"/>
        <pin num="B5" name="VCONN" type="bidirectional"/>
        <pin num="B9" name="VBUS" type="passive"/>
        <pin num="B12" name="GND" type="passive"/>
        <pin num="S1" name="SHIELD" type="passive"/>
      </pins>
    </libpart>
    <libpart lib="Connector_Generic" part="Conn_01x04">
      <description>Generic connector, single row, 01x04, script generated (kicad-library-utils/schlib/autogen/connector/)</description>
      <docs>~</docs>
      <footprints>
        <fp>Connector*:*_1x??_*</fp>
      </footprints>
      <fields>
        <field name="Reference">J</field>
        <field name="Value">Conn_01x04</field>
        <field name="Datasheet">~</field>
      </fields>
      <pins>
        <pin num="1" name="Pin_1" type="passive"/>
        <pin num="2" name="Pin_2" type="passive"/>
        <pin num="3" name="Pin_3" type="passive"/>
        <pin num="4" name="Pin_4" type="passive"/>
      </pins>
    </libpart>
    <libpart lib="Device" part="C">
      <description>Unpolarized capacitor</description>
      <docs>~</docs>
      <footprints>
        <fp>C_*</fp>
      </footprints>
      <fields>
        <field name="Reference">C</field>
        <field name="Value">C</field>
        <field name="Datasheet">~</field>
      </fields>
      <pins>
        <pin num="1" name="" type="passive"/>
        <pin num="2" name="" type="passive"/>
      </pins>
    </libpart>
    <libpart lib="Device" part="C_Small">
      <description>Unpolarized capacitor, small symbol</description>
      <docs>~</docs>
      <footprints>
        <fp>C_*</fp>
      </footprints>
      <fields>
        <field name="Reference">C</field>
        <field name="Value">C_Small</field>
        <field name="Datasheet">~</field>
      </fields>
      <pins>
        <pin num="1" name="" type="passive"/>
        <pin num="2" name="" type="passive"/>
      </pins>
    </libpart>
    <libpart lib="Device" part="R">
      <description>Resistor</description>
      <docs>~</docs>
      <footprints>
        <fp>R_*</fp>
      </footprints>
      <fields>
        <field name="Reference">R</field>
        <field name="Value">R</field>
        <field name="Datasheet">~</field>
      </fields>
      <pins>
        <pin num="1" name="" type="passive"/>
        <pin num="2" name="" type="passive"/>
      </pins>
    </libpart>
    <libpart lib="Espressif" part="ESP32-C3-MINI-1">
      <description>ESP32-C3-MINI-1 family is an ultra-low-power MCU-based SoC solution that supports 2.4 GHz Wi-Fi and Bluetooth®Low Energy (Bluetooth LE).</description>
      <docs>https://www.espressif.com/sites/default/files/documentation/esp32-c3-mini-1_datasheet_en.pdf</docs>
      <fields>
        <field name="Reference">U</field>
        <field name="Value">ESP32-C3-MINI-1</field>
        <field name="Footprint">Espressif:ESP32-C3-MINI-1</field>
        <field name="Datasheet">https://www.espressif.com/sites/default/files/documentation/esp32-c3-mini-1_datasheet_en.pdf</field>
      </fields>
      <pins>
        <pin num="1" name="GND" type="power_in"/>
        <pin num="2" name="GND" type="passive"/>
        <pin num="3" name="3V3" type="power_in"/>
        <pin num="4" name="NC" type="no_connect"/>
        <pin num="5" name="GPIO2/ADC1_CH2" type="bidirectional"/>
        <pin num="6" name="GPIO3/ADC1_CH3" type="bidirectional"/>
        <pin num="7" name="NC" type="no_connect"/>
        <pin num="8" name="EN/CHIP_PU" type="input"/>
        <pin num="9" name="NC" type="no_connect"/>
        <pin num="10" name="NC" type="no_connect"/>
        <pin num="11" name="GND" type="passive"/>
        <pin num="12" name="GPIO0/ADC1_CH0/XTAL_32K_P" type="bidirectional"/>
        <pin num="13" name="GPIO1/ADC1_CH1/XTAL_32K_N" type="bidirectional"/>
        <pin num="14" name="GND" type="passive"/>
        <pin num="15" name="NC" type="no_connect"/>
        <pin num="16" name="GPIO10" type="bidirectional"/>
        <pin num="17" name="NC" type="no_connect"/>
        <pin num="18" name="GPIO4/ADC1_CH4" type="bidirectional"/>
        <pin num="19" name="GPIO5/ADC2_CH0" type="bidirectional"/>
        <pin num="20" name="GPIO6" type="bidirectional"/>
        <pin num="21" name="GPIO7" type="bidirectional"/>
        <pin num="22" name="GPIO8" type="bidirectional"/>
        <pin num="23" name="GPIO9" type="bidirectional"/>
        <pin num="24" name="NC" type="no_connect"/>
        <pin num="25" name="NC" type="no_connect"/>
        <pin num="26" name="GPIO18/USB_D-" type="bidirectional"/>
        <pin num="27" name="GPIO19/USB_D+" type="bidirectional"/>
        <pin num="28" name="NC" type="no_connect"/>
        <pin num="29" name="NC" type="no_connect"/>
        <pin num="30" name="GPIO20/U0RXD" type="bidirectional"/>
        <pin num="31" name="GPIO21/U0TXD" type="bidirectional"/>
        <pin num="32" name="NC" type="no_connect"/>
        <pin num="33" name="NC" type="no_connect"/>
        <pin num="34" name="NC" type="no_connect"/>
        <pin num="35" name="NC" type="no_connect"/>
        <pin num="36" name="GND" type="passive"/>
        <pin num="37" name="GND" type="passive"/>
        <pin num="38" name="GND" type="passive"/>
        <pin num="39" name="GND" type="passive"/>
        <pin num="40" name="GND" type="passive"/>
        <pin num="41" name="GND" type="passive"/>
        <pin num="42" name="GND" type="passive"/>
        <pin num="43" name="GND" type="passive"/>
        <pin num="44" name="GND" type="passive"/>
        <pin num="45" name="GND" type="passive"/>
        <pin num="46" name="GND" type="passive"/>
        <pin num="47" name="GND" type="passive"/>
        <pin num="48" name="GND" type="passive"/>
        <pin num="49" name="GND" type="passive"/>
        <pin num="50" name="GND" type="passive"/>
        <pin num="51" name="GND" type="passive"/>
        <pin num="52" name="GND" type="passive"/>
        <pin num="53" name="GND" type="passive"/>
      </pins>
    </libpart>
    <libpart lib="Interface_CAN_LIN" part="SN65HVD230">
      <description>CAN Bus Transceivers, 3.3V, 1Mbps, Low-Power capabilities, SOIC-8</description>
      <docs>http://www.ti.com/lit/ds/symlink/sn65hvd230.pdf</docs>
      <footprints>
        <fp>SOIC*3.9x4.9mm*P1.27mm*</fp>
      </footprints>
      <fields>
        <field name="Reference">U</field>
        <field name="Value">SN65HVD230</field>
        <field name="Footprint">Package_SO:SOIC-8_3.9x4.9mm_P1.27mm</field>
        <field name="Datasheet">http://www.ti.com/lit/ds/symlink/sn65hvd230.pdf</field>
      </fields>
      <pins>
        <pin num="1" name="D" type="input"/>
        <pin num="2" name="GND" type="power_in"/>
        <pin num="3" name="VCC" type="power_in"/>
        <pin num="4" name="R" type="output"/>
        <pin num="5" name="Vref" type="output"/>
        <pin num="6" name="CANL" type="bidirectional"/>
        <pin num="7" name="CANH" type="bidirectional"/>
        <pin num="8" name="Rs" type="input"/>
      </pins>
    </libpart>
    <libpart lib="Mechanical" part="MountingHole">
      <description>Mounting Hole without connection</description>
      <docs>~</docs>
      <footprints>
        <fp>MountingHole*</fp>
      </footprints>
      <fields>
        <field name="Reference">H</field>
        <field name="Value">MountingHole</field>
        <field name="Datasheet">~</field>
      </fields>
    </libpart>
    <libpart lib="Regulator_Linear" part="AP2112K-3.3">
      <description>600mA low dropout linear regulator, with enable pin, 3.8V-6V input voltage range, 3.3V fixed positive output, SOT-23-5</description>
      <docs>https://www.diodes.com/assets/Datasheets/AP2112.pdf</docs>
      <footprints>
        <fp>SOT?23?5*</fp>
      </footprints>
      <fields>
        <field name="Reference">U</field>
        <field name="Value">AP2112K-3.3</field>
        <field name="Footprint">Package_TO_SOT_SMD:SOT-23-5</field>
        <field name="Datasheet">https://www.diodes.com/assets/Datasheets/AP2112.pdf</field>
      </fields>
      <pins>
        <pin num="1" name="VIN" type="power_in"/>
        <pin num="2" name="GND" type="power_in"/>
        <pin num="3" name="EN" type="input"/>
        <pin num="4" name="NC" type="no_connect"/>
        <pin num="5" name="VOUT" type="power_out"/>
      </pins>
    </libpart>
    <libpart lib="Transistor_FET" part="BSS214NW">
      <description>20V Vds, 1.5A Id, N-Channel MOSFET, SOT-323</description>
      <docs>https://www.infineon.com/dgdl/Infineon-BSS214NW-DS-v02_02-en.pdf?fileId=db3a30431b3e89eb011b695aebc01bde</docs>
      <footprints>
        <fp>SOT?323*</fp>
      </footprints>
      <fields>
        <field name="Reference">Q</field>
        <field name="Value">BSS214NW</field>
        <field name="Footprint">Package_TO_SOT_SMD:SOT-323_SC-70</field>
        <field name="Datasheet">https://www.infineon.com/dgdl/Infineon-BSS214NW-DS-v02_02-en.pdf?fileId=db3a30431b3e89eb011b695aebc01bde</field>
      </fields>
      <pins>
        <pin num="1" name="G" type="input"/>
        <pin num="2" name="S" type="passive"/>
        <pin num="3" name="D" type="passive"/>
      </pins>
    </libpart>
  </libparts>
  <libraries>
    <library logical="Connector">
      <uri>/app/extensions/Library/symbols//Connector.kicad_sym</uri>
    </library>
    <library logical="Connector_Generic">
      <uri>/app/extensions/Library/symbols//Connector_Generic.kicad_sym</uri>
    </library>
    <library logical="Device">
      <uri>/app/extensions/Library/symbols//Device.kicad_sym</uri>
    </library>
    <library logical="Espressif">
      <uri>/home/johannes/.var/app/org.kicad.KiCad/data/kicad/7.0/symbols/Espressif.kicad_sym</uri>
    </library>
    <library logical="Interface_CAN_LIN">
      <uri>/app/extensions/Library/symbols//Interface_CAN_LIN.kicad_sym</uri>
    </library>
    <library logical="Mechanical">
      <uri>/app/extensions/Library/symbols//Mechanical.kicad_sym</uri>
    </library>
    <library logical="Regulator_Linear">
      <uri>/app/extensions/Library/symbols//Regulator_Linear.kicad_sym</uri>
    </library>
    <library logical="Transistor_FET">
      <uri>/app/extensions/Library/symbols//Transistor_FET.kicad_sym</uri>
    </library>
  </libraries>
  <nets>
    <net code="1" name="+3.3V">
      <node ref="U5" pin="3" pinfunction="3V3" pintype="power_in"/>
    </net>
    <net code="2" name="+3V3">
      <node ref="C2" pin="1" pintype="passive"/>
      <node ref="C3" pin="1" pintype="passive"/>
      <node ref="C4" pin="2" pintype="passive"/>
      <node ref="U1" pin="5" pinfunction="VOUT" pintype="power_out"/>
      <node ref="U2" pin="3" pinfunction="VCC" pintype="power_in"/>
    </net>
    <net code="3" name="/CAN_RX">
      <node ref="U2" pin="4" pinfunction="R" pintype="output"/>
      <node ref="U5" pin="23" pinfunction="GPIO9" pintype="bidirectional"/>
    </net>
    <net code="4" name="/CAN_TX">
      <node ref="U2" pin="1" pinfunction="D" pintype="input"/>
      <node ref="U5" pin="22" pinfunction="GPIO8" pintype="bidirectional"/>
    </net>
    <net code="5" name="/D+">
      <node ref="P1" pin="A6" pinfunction="D+" pintype="bidirectional"/>
      <node ref="U5" pin="27" pinfunction="GPIO19/USB_D+" pintype="bidirectional"/>
    </net>
    <net code="6" name="/D-">
      <node ref="P1" pin="A7" pinfunction="D-" pintype="bidirectional"/>
      <node ref="U5" pin="26" pinfunction="GPIO18/USB_D-" pintype="bidirectional"/>
    </net>
    <net code="7" name="/RXD">
      <node ref="U5" pin="30" pinfunction="GPIO20/U0RXD" pintype="bidirectional"/>
    </net>
    <net code="8" name="/TERM">
      <node ref="Q1" pin="1" pinfunction="G" pintype="input"/>
      <node ref="Q2" pin="1" pinfunction="G" pintype="input"/>
      <node ref="U5" pin="19" pinfunction="GPIO5/ADC2_CH0" pintype="bidirectional"/>
    </net>
    <net code="9" name="/TXD">
      <node ref="U5" pin="31" pinfunction="GPIO21/U0TXD" pintype="bidirectional"/>
    </net>
    <net code="10" name="CAN_H">
      <node ref="J1" pin="2" pinfunction="Pin_2" pintype="passive"/>
      <node ref="Q1" pin="2" pinfunction="S" pintype="passive"/>
      <node ref="R2" pin="1" pintype="passive"/>
      <node ref="U2" pin="7" pinfunction="CANH" pintype="bidirectional"/>
    </net>
    <net code="11" name="CAN_L">
      <node ref="J1" pin="3" pinfunction="Pin_3" pintype="passive"/>
      <node ref="Q2" pin="2" pinfunction="S" pintype="passive"/>
      <node ref="R3" pin="1" pintype="passive"/>
      <node ref="U2" pin="6" pinfunction="CANL" pintype="bidirectional"/>
    </net>
    <net code="12" name="GND">
      <node ref="C1" pin="2" pintype="passive"/>
      <node ref="C2" pin="2" pintype="passive"/>
      <node ref="C3" pin="2" pintype="passive"/>
      <node ref="C4" pin="1" pintype="passive"/>
      <node ref="J1" pin="4" pinfunction="Pin_4" pintype="passive"/>
      <node ref="P1" pin="A1" pinfunction="GND" pintype="passive"/>
      <node ref="P1" pin="A12" pinfunction="GND" pintype="passive"/>
      <node ref="P1" pin="B1" pinfunction="GND" pintype="passive"/>
      <node ref="P1" pin="B12" pinfunction="GND" pintype="passive"/>
      <node ref="P1" pin="S1" pinfunction="SHIELD" pintype="passive"/>
      <node ref="Q1" pin="3" pinfunction="D" pintype="passive"/>
      <node ref="Q2" pin="3" pinfunction="D" pintype="passive"/>
      <node ref="R1" pin="2" pintype="passive"/>
      <node ref="R2" pin="2" pintype="passive"/>
      <node ref="R3" pin="2" pintype="passive"/>
      <node ref="TP1" pin="1" pinfunction="1" pintype="passive"/>
      <node ref="TP2" pin="1" pinfunction="1" pintype="passive"/>
      <node ref="TP3" pin="1" pinfunction="1" pintype="passive"/>
      <node ref="TP4" pin="1" pinfunction="1" pintype="passive"/>
      <node ref="U1" pin="2" pinfunction="GND" pintype="power_in"/>
      <node ref="U2" pin="2" pinfunction="GND" pintype="power_in"/>
      <node ref="U5" pin="1" pinfunction="GND" pintype="power_in"/>
      <node ref="U5" pin="11" pinfunction="GND" pintype="passive"/>
      <node ref="U5" pin="14" pinfunction="GND" pintype="passive"/>
      <node ref="U5" pin="2" pinfunction="GND" pintype="passive"/>
      <node ref="U5" pin="36" pinfunction="GND" pintype="passive"/>
      <node ref="U5" pin="37" pinfunction="GND" pintype="passive"/>
      <node ref="U5" pin="38" pinfunction="GND" pintype="passive"/>
      <node ref="U5" pin="39" pinfunction="GND" pintype="passive"/>
      <node ref="U5" pin="40" pinfunction="GND" pintype="passive"/>
      <node ref="U5" pin="41" pinfunction="GND" pintype="passive"/>
      <node ref="U5" pin="42" pinfunction="GND" pintype="passive"/>
      <node ref="U5" pin="43" pinfunction="GND" pintype="passive"/>
      <node ref="U5" pin="44" pinfunction="GND" pintype="passive"/>
      <node ref="U5" pin="45" pinfunction="GND" pintype="passive"/>
      <node ref="U5" pin="46" pinfunction="GND" pintype="passive"/>
      <node ref="U5" pin="47" pinfunction="GND" pintype="passive"/>
      <node ref="U5" pin="48" pinfunction="GND" pintype="passive"/>
      <node ref="U5" pin="49" pinfunction="GND" pintype="passive"/>
      <node ref="U5" pin="50" pinfunction="GND" pintype="passive"/>
      <node ref="U5" pin="51" pinfunction="GND" pintype="passive"/>
      <node ref="U5" pin="52" pinfunction="GND" pintype="passive"/>
      <node ref="U5" pin="53" pinfunction="GND" pintype="passive"/>
    </net>
    <net code="13" name="Net-(P1-CC)">
      <node ref="P1" pin="A5" pinfunction="CC" pintype="bidirectional"/>
      <node ref="R1" pin="1" pintype="passive"/>
    </net>
    <net code="14" name="VBUS">
      <node ref="C1" pin="1" pintype="passive"/>
      <node ref="J1" pin="1" pinfunction="Pin_1" pintype="passive"/>
      <node ref="P1" pin="A4" pinfunction="VBUS" pintype="passive"/>
      <node ref="P1" pin="A9" pinfunction="VBUS" pintype="passive"/>
      <node ref="P1" pin="B4" pinfunction="VBUS" pintype="passive"/>
      <node ref="P1" pin="B9" pinfunction="VBUS" pintype="passive"/>
      <node ref="U1" pin="1" pinfunction="VIN" pintype="power_in"/>
      <node ref="U1" pin="3" pinfunction="EN" pintype="input"/>
    </net>
    <net code="15" name="unconnected-(P1-VCONN-PadB5)">
      <node ref="P1" pin="B5" pinfunction="VCONN" pintype="bidirectional+no_connect"/>
    </net>
    <net code="16" name="unconnected-(U1-NC-Pad4)">
      <node ref="U1" pin="4" pinfunction="NC" pintype="no_connect"/>
    </net>
    <net code="17" name="unconnected-(U2-Rs-Pad8)">
      <node ref="U2" pin="8" pinfunction="Rs" pintype="input+no_connect"/>
    </net>
    <net code="18" name="unconnected-(U2-Vref-Pad5)">
      <node ref="U2" pin="5" pinfunction="Vref" pintype="output+no_connect"/>
    </net>
    <net code="19" name="unconnected-(U5-EN{slash}CHIP_PU-Pad8)">
      <node ref="U5" pin="8" pinfunction="EN/CHIP_PU" pintype="input+no_connect"/>
    </net>
    <net code="20" name="unconnected-(U5-GPIO0{slash}ADC1_CH0{slash}XTAL_32K_P-Pad12)">
      <node ref="U5" pin="12" pinfunction="GPIO0/ADC1_CH0/XTAL_32K_P" pintype="bidirectional+no_connect"/>
    </net>
    <net code="21" name="unconnected-(U5-GPIO1{slash}ADC1_CH1{slash}XTAL_32K_N-Pad13)">
      <node ref="U5" pin="13" pinfunction="GPIO1/ADC1_CH1/XTAL_32K_N" pintype="bidirectional+no_connect"/>
    </net>
    <net code="22" name="unconnected-(U5-GPIO2{slash}ADC1_CH2-Pad5)">
      <node ref="U5" pin="5" pinfunction="GPIO2/ADC1_CH2" pintype="bidirectional+no_connect"/>
    </net>
    <net code="23" name="unconnected-(U5-GPIO3{slash}ADC1_CH3-Pad6)">
      <node ref="U5" pin="6" pinfunction="GPIO3/ADC1_CH3" pintype="bidirectional+no_connect"/>
    </net>
    <net code="24" name="unconnected-(U5-GPIO4{slash}ADC1_CH4-Pad18)">
      <node ref="U5" pin="18" pinfunction="GPIO4/ADC1_CH4" pintype="bidirectional+no_connect"/>
    </net>
    <net code="25" name="unconnected-(U5-GPIO6-Pad20)">
      <node ref="U5" pin="20" pinfunction="GPIO6" pintype="bidirectional+no_connect"/>
    </net>
    <net code="26" name="unconnected-(U5-GPIO7-Pad21)">
      <node ref="U5" pin="21" pinfunction="GPIO7" pintype="bidirectional+no_connect"/>
    </net>
    <net code="27" name="unconnected-(U5-GPIO10-Pad16)">
      <node ref="U5" pin="16" pinfunction="GPIO10" pintype="bidirectional+no_connect"/>
    </net>
    <net code="28" name="unconnected-(U5-NC-Pad4)">
      <node ref="U5" pin="4" pinfunction="NC" pintype="no_connect"/>
    </net>
    <net code="29" name="unconnected-(U5-NC-Pad7)">
      <node ref="U5" pin="7" pinfunction="NC" pintype="no_connect"/>
    </net>
    <net code="30" name="unconnected-(U5-NC-Pad9)">
      <node ref="U5" pin="9" pinfunction="NC" pintype="no_connect"/>
    </net>
    <net code="31" name="unconnected-(U5-NC-Pad10)">
      <node ref="U5" pin="10" pinfunction="NC" pintype="no_connect"/>
    </net>
    <net code="32" name="unconnected-(U5-NC-Pad15)">
      <node ref="U5" pin="15" pinfunction="NC" pintype="no_connect"/>
    </net>
    <net code="33" name="unconnected-(U5-NC-Pad17)">
      <node ref="U5" pin="17" pinfunction="NC" pintype="no_connect"/>
    </net>
    <net code="34" name="unconnected-(U5-NC-Pad24)">
      <node ref="U5" pin="24" pinfunction="NC" pintype="no_connect"/>
    </net>
    <net code="35" name="unconnected-(U5-NC-Pad25)">
      <node ref="U5" pin="25" pinfunction="NC" pintype="no_connect"/>
    </net>
    <net code="36" name="unconnected-(U5-NC-Pad28)">
      <node ref="U5" pin="28" pinfunction="NC" pintype="no_connect"/>
    </net>
    <net code="37" name="unconnected-(U5-NC-Pad29)">
      <node ref="U5" pin="29" pinfunction="NC" pintype="no_connect"/>
    </net>
    <net code="38" name="unconnected-(U5-NC-Pad32)">
      <node ref="U5" pin="32" pinfunction="NC" pintype="no_connect"/>
    </net>
    <net code="39" name="unconnected-(U5-NC-Pad33)">
      <node ref="U5" pin="33" pinfunction="NC" pintype="no_connect"/>
    </net>
    <net code="40" name="unconnected-(U5-NC-Pad34)">
      <node ref="U5" pin="34" pinfunction="NC" pintype="no_connect"/>
    </net>
    <net code="41" name="unconnected-(U5-NC-Pad35)">
      <node ref="U5" pin="35" pinfunction="NC" pintype="no_connect"/>
    </net>
  </nets>
</export>
